{"Adaptability": "Adaptabilité", "Aftermath": "Boom Final", "Air Lock": "Air Lock", "Analytic": "Analyste", "Anger Point": "Colérique", "Anticipation": "Anticipation", "Arena Trap": "Piège Sable", "Bad Dreams": "Mauvais Rêve", "Battle Armor": "Armurbaston", "Big Pecks": "Cœur de Coq", "Blaze": "Brasier", "Chlorophyll": "Chlorophylle", "Clear Body": "Corps Sain", "Cloud Nine": "Ciel Gris", "Color Change": "Homochromie", "Competitive": "Battant", "Compound Eyes": "Œil Composé", "Contrary": "Contestation", "Cursed Body": "Corps Maudit", "Cute Charm": "Joli Sourire", "Damp": "Moiteur", "Defeatist": "Défaitiste", "Defiant": "Acharné", "Download": "Télécharge", "Drizzle": "Crachin", "Drought": "Sécheresse", "Dry Skin": "Peau Sèche", "Early Bird": "Matinal", "Effect Spore": "Pose Spore", "Filter": "Filtre", "Flame Body": "Corps Ardent", "Flare Boost": "Rage Brûlure", "Flash Fire": "Torche", "Flower Gift": "Don Floral", "Forecast": "Météo", "Forewarn": "Prédiction", "Friend Guard": "Garde-Ami", "Frisk": "Fouille", "Gluttony": "Gloutonnerie", "Guts": "Cran", "Harvest": "Récolte", "Healer": "Cœur Soin", "Heatproof": "Ignifugé", "Heavy Metal": "Heavy Metal", "Honey Gather": "Cherche Miel", "Huge Power": "Coloforce", "Hustle": "Agitation", "Hydration": "Hydratation", "Hyper Cutter": "Hyper Cutter", "Ice Body": "Corps Gel", "Illuminate": "Lumiattirance", "Illusion": "Illusion", "Immunity": "Vaccin", "Imposter": "Imposteur", "Infiltrator": "Infiltration", "Inner Focus": "Attention", "Insomnia": "Insomnia", "Intimidate": "Intimidation", "Iron Barbs": "Épine de Fer", "Iron Fist": "Poing de Fer", "Justified": "Cœur Noble", "Keen Eye": "Regard Vif", "Klutz": "Maladresse", "Leaf Guard": "Feuille Garde", "Levitate": "Lévitation", "Light Metal": "Light Metal", "Lightning Rod": "Paratonnerre", "Limber": "Échauffement", "Liquid Ooze": "Suintement", "Magic Bounce": "Miroir Magik", "Magic Guard": "Garde Magik", "Magma Armor": "Armumagma", "Magnet Pull": "Magnépiège", "Marvel Scale": "Écaille Spéciale", "Minus": "Moins", "Mold Breaker": "Brise Moule", "Moody": "Lunatique", "Motor Drive": "Motorisé", "Moxie": "Impudence", "Multiscale": "Multiécaille", "Multitype": "Multi-Type", "Mummy": "Momie", "Natural Cure": "Médic Nature", "Neutralizing Gas": "Gaz Inhibiteur", "No Guard": "Annule Garde", "Normalize": "Normalise", "Oblivious": "Benêt", "Overcoat": "Envelocape", "Overgrow": "Engrais", "Own Tempo": "Tempo Perso", "Pickpocket": "Pickpocket", "Pickup": "Ramassage", "Plus": "Plus", "Poison Heal": "Soin Poison", "Poison Point": "Point Poison", "Poison Touch": "Toxitouche", "Prankster": "Farceur", "Pressure": "Pression", "Protean": "Protéen", "Pure Power": "Force Pure", "Quick Feet": "Pied Véloce", "Rain Dish": "Cuvette", "Rattled": "Phobique", "Reckless": "Téméraire", "Regenerator": "Régé-Force", "Rivalry": "Rivalité", "Rock Head": "Tête de Roc", "Rough Skin": "Peau Dure", "Run Away": "Fuite", "Sand Force": "Force Sable", "Sand Rush": "Baigne Sable", "Sand Stream": "Sable Volant", "Sand Veil": "Voile Sable", "Sap Sipper": "Herbivore", "Scrappy": "Querelleur", "Serene Grace": "Sérénité", "Shadow Tag": "Marque Ombre", "Sharpness": "Incisif", "Shed Skin": "Mue", "Sheer Force": "Sans Limite", "Shell Armor": "Coque Armure", "Shield Dust": "Écran Poudre", "Simple": "Simple", "Skill Link": "Multi-Coups", "Slow Start": "Début Calme", "Slush Rush": "Chasse-Neige", "Sniper": "Sniper", "Snow Cloak": "Rideau Neige", "Snow Warning": "Alerte Neige", "Solar Power": "Force Soleil", "Solid Rock": "Solide Roc", "Soundproof": "Anti-Bruit", "Speed Boost": "Turbo", "Stall": "Frein", "Static": "Statik", "Steadfast": "Impassible", "Stench": "Puanteur", "Sticky Hold": "Glu", "Storm Drain": "Lavabo", "Sturdy": "Fermeté", "Suction Cups": "Ventouse", "Super Luck": "Chanceux", "Swarm": "Essaim", "Swift Swim": "Glissade", "Synchronize": "Synchro", "Tangled Feet": "Pieds Confus", "Technician": "Technicien", "Telepathy": "Télépathe", "Teravolt": "Téra-Voltage", "Thick Fat": "Isograisse", "Tinted Lens": "Lentiteintée", "Torrent": "Torrent", "Toxic Boost": "Rage Poison", "Trace": "Calque", "Truant": "Absentéisme", "Turboblaze": "Turbo Brasier", "Unaware": "Inconscient", "Unburden": "Délestage", "Unnerve": "Tension", "Victory Star": "Victorieux", "Vital Spirit": "Esprit Vital", "Volt Absorb": "Absorbe-Volt", "Water Absorb": "Absorbe-Eau", "Water Veil": "Ignifu-Voile", "Weak Armor": "Armurouillée", "White Smoke": "Écran Fumée", "Wind Rider": "Aéroporté", "Wonder Guard": "Garde Mystik", "Wonder Skin": "Peau Miracle", "Zen Mode": "Mode Transe"}